mymathlib/__init__.py
mymathlib/calc.py
mymathlib_kuwae-0.1.0.dist-info/LICENSE
mymathlib_kuwae-0.1.0.dist-info/METADATA
mymathlib_kuwae-0.1.0.dist-info/WHEEL
mymathlib_kuwae-0.1.0.dist-info/top_level.txt
mymathlib_kuwae-0.1.0.dist-info/RECORD
